aio/api/nist/__init__.py
aio/api/nist/exceptions.py
aio/api/nist/interface.py
aio/api/nist/nist.py
aio/api/nist/py.typed
aio/api/nist/typing.py
aio/api/nist/abstract/__init__.py
aio/api/nist/abstract/cpe.py
aio/api/nist/abstract/cve.py
aio/api/nist/abstract/downloader.py
aio/api/nist/abstract/matcher.py
aio/api/nist/abstract/parser.py
aio.api.nist-0.0.4.dist-info/METADATA
aio.api.nist-0.0.4.dist-info/WHEEL
aio.api.nist-0.0.4.dist-info/namespace_packages.txt
aio.api.nist-0.0.4.dist-info/top_level.txt
aio.api.nist-0.0.4.dist-info/RECORD
